MANIFEST.in
README.md
setup.py
yxt_nlp_toolkit/__init__.py
yxt_nlp_toolkit.egg-info/PKG-INFO
yxt_nlp_toolkit.egg-info/SOURCES.txt
yxt_nlp_toolkit.egg-info/dependency_links.txt
yxt_nlp_toolkit.egg-info/not-zip-safe
yxt_nlp_toolkit.egg-info/requires.txt
yxt_nlp_toolkit.egg-info/top_level.txt
yxt_nlp_toolkit/common/__init__.py
yxt_nlp_toolkit/common/lang.py
yxt_nlp_toolkit/common/vocab.py
yxt_nlp_toolkit/embedding/__init__.py
yxt_nlp_toolkit/embedding/fasttext.py
yxt_nlp_toolkit/embedding/general.py
yxt_nlp_toolkit/embedding/gensims.py
yxt_nlp_toolkit/embedding/wordembedding.py
yxt_nlp_toolkit/utils/__init__.py
yxt_nlp_toolkit/utils/str_algo.py
yxt_nlp_toolkit/utils/tokenizer.py
yxt_nlp_toolkit/utils/jieba_dict/__init__.py
yxt_nlp_toolkit/utils/jieba_dict/dict.dat
yxt_nlp_toolkit/utils/jieba_dict/stopwords.dat