Metadata-Version: 1.1
Name: yxt-nlp-toolkit
Version: 0.2.0
Summary: common utils for yxt nlp processing
Home-page: https://github.com/junix/yxt_nlp_toolkit.git
Author: wanglijun
Author-email: juns1984@qq.com
License: MIT
Keywords: yunxuetang nlp
Platform: UNKNOWN
Classifier: Development Status :: 3 - Alpha
Classifier: License :: OSI Approved :: MIT License
Classifier: Programming Language :: Python :: 3.6
Classifier: Topic :: Text Processing :: Linguistic
